cleature/__init__.py
cleature/cli.py
cleature/config_merge_handler.py
cleature/core.py
cleature-0.1.0.dist-info/licenses/LICENSE
cleature-0.1.0.dist-info/METADATA
cleature-0.1.0.dist-info/WHEEL
cleature-0.1.0.dist-info/entry_points.txt
cleature-0.1.0.dist-info/top_level.txt
cleature-0.1.0.dist-info/RECORD
