Metadata-Version: 2.4
Name: cleature
Version: 0.1.0
Summary: A lightweight Python templating engine for CHTML files with includes and variable substitution support.
Author-email: CodemasterUnited <codemasterunited@gmail.com>
License: MIT
Keywords: templating,static site,html,chtml,include,variable
Classifier: Programming Language :: Python :: 3
Classifier: Programming Language :: Python :: 3.7
Classifier: License :: OSI Approved :: MIT License
Classifier: Intended Audience :: Developers
Classifier: Operating System :: OS Independent
Classifier: Topic :: Software Development :: Build Tools
Classifier: Topic :: Internet :: WWW/HTTP :: Site Management
Requires-Python: >=3.7
License-File: LICENSE
Dynamic: license-file
